textkit/__init__.py
textkit/cli.py
textkit/coerce.py
textkit/download.py
textkit/utils.py
textkit/data/stopwords/english.txt
textkit/data/stopwords/german.txt
textkit/filter/__init__.py
textkit/filter/filter_lengths.py
textkit/filter/filter_punc.py
textkit/filter/filter_words.py
textkit/package/__init__.py
textkit/package/texts_to_json.py
textkit/package/tokens_to_json.py
textkit/package/tokens_to_text.py
textkit/tokenize/__init__.py
textkit/tokenize/bigrams.py
textkit/tokenize/ngrams.py
textkit/tokenize/punc.py
textkit/tokenize/sentences.py
textkit/tokenize/words.py
textkit/transform/__init__.py
textkit/transform/newlines.py
textkit/transform/tokens_to_counts.py
textkit/transform/tokens_to_lower.py
textkit/transform/tokens_to_pos.py
textkit/transform/tokens_to_stem.py
textkit/transform/tokens_to_top_bigrams.py
textkit/transform/tokens_to_upper.py
textkit/transform/transliterate.py
textkit-0.2.3.dist-info/DESCRIPTION.rst
textkit-0.2.3.dist-info/METADATA
textkit-0.2.3.dist-info/RECORD
textkit-0.2.3.dist-info/WHEEL
textkit-0.2.3.dist-info/entry_points.txt
textkit-0.2.3.dist-info/metadata.json
textkit-0.2.3.dist-info/top_level.txt
