Metadata-Version: 2.0
Name: textkit
Version: 0.2.3
Summary: Simple text analysis from the command line
Home-page: https://github.com/learntextvis/textkit
Author: Learn Text Vis Team
Author-email: landham@gmail.com
License: MIT
Keywords: text,analysis,textkit
Platform: UNKNOWN
Classifier: Development Status :: 3 - Alpha
Classifier: Environment :: Console
Classifier: Intended Audience :: Developers
Classifier: Intended Audience :: End Users/Desktop
Classifier: Intended Audience :: Science/Research
Classifier: License :: OSI Approved :: MIT License
Classifier: Natural Language :: English
Classifier: Operating System :: OS Independent
Classifier: Programming Language :: Python
Classifier: Programming Language :: Python :: 2.7
Classifier: Programming Language :: Python :: 3.4
Classifier: Topic :: Utilities
Requires-Dist: chardet (>=2.3.0)
Requires-Dist: click (>=6.2)
Requires-Dist: nltk (>=3.1)
Requires-Dist: unidecode (>=0.4.20)
